nmutils/__init__.py
nmutils/c_pythagorean_triples.cpython-37m-darwin.so
nmutils/miller_rabin.cpython-37m-darwin.so
nmutils/primes.py
nmutils/pythagorean_triples.py
nmutils/sqrt_expansion.py
nmutils-0.0.10.dist-info/LICENSE
nmutils-0.0.10.dist-info/METADATA
nmutils-0.0.10.dist-info/WHEEL
nmutils-0.0.10.dist-info/top_level.txt
nmutils-0.0.10.dist-info/RECORD
