Metadata-Version: 2.1
Name: nmutils
Version: 0.0.10
Summary: A collection of mathematical utilities, primarily to help with repetitive elements of solving problems hosted at Project Euler
Home-page: https://github.com/neilmarshall/nmutils.git
Author: Neil Marshall
Author-email: neil.marshall@dunelm.org.uk
License: UNKNOWN
Project-URL: Documentation, http://www.nmutils-documentation.com.s3-website.eu-west-2.amazonaws.com/index.html
Platform: UNKNOWN
